{"entity":"goals","stats":{"pageInfo":{"page":0,"numPages":13,"pageSize":25,"numEntries":303},"content":[{"owner":{"playerId":312560.0,"info":{"position":"F","shirtNum":9.0,"positionInfo":"Centre Striker","loan":false},"nationalTeam":{"isoCode":"NO","country":"Norway","demonym":"Norwegian"},"currentTeam":{"name":"Manchester City","club":{"name":"Manchester City","abbr":"MCI","id":11.0},"teamType":"FIRST","shortName":"Man City","id":11.0},"birth":{"date":{"millis":9.641376E11,"label":"21 July 2000"},"country":{"isoCode":"GB-ENG","country":"England","demonym":"English"},"place":"Leeds"},"age":"24 years 362 days","name":{"display":"Erling Haaland","first":"Erling","last":"Haaland"},"id":65970.0},"rank":1.0,"name":"goals","value":27.0,"description":"Todo: goals","additionalInfo":{}},{"owner":{"playerId":346777.0,"info":{"position":"M","shirtNum":10.0,"positionInfo":"Attacking Midfielder","loan":false},"nationalTeam":{"isoCode":"GB-ENG","country":"England","demonym":"English"},"currentTeam":{"name":"Chelsea","club":{"name":"Chelsea","abbr":"CHE","id":4.0},"teamType":"FIRST","shortName":"Chelsea","id":4.0},"birth":{"date":{"millis":1.0206432E12,"label":"6 May 2002"},"country":{"isoCode":"GB-ENG","country":"England","demonym":"English"},"place":"Manchester"},"age":"23 years 73 days","name":{"display":"Cole Palmer","first":"Cole","middle":"Jermaine","last":"Palmer"},"id":49293.0},"rank":2.0,"name":"goals","value":22.0,"description":"Todo: goals","additionalInfo":{}},{"owner":{"playerId":324327.0,"info":{"position":"F","shirtNum":14.0,"positionInfo":"Centre Striker","loan":false},"nationalTeam":{"isoCode":"SE","country":"Sweden","demonym":"Swedish"},"currentTeam":{"name":"Newcastle United","club":{"name":"Newcastle United","abbr":"NEW","id":23.0},"teamType":"FIRST","shortName":"Newcastle","id":23.0},"birth":{"date":{"millis":9.37872E11,"label":"21 September 1999"},"country":{"isoCode":"SE","country":"Sweden","demonym":"Swedish"},"place":"Solna"},"age":"25 years 300 days","name":{"display":"Alexander Isak","first":"Alexander","last":"Isak"},"id":21737.0},"rank":3.0,"name":"goals","value":21.0,"description":"Todo: goals","additionalInfo":{}},{"owner":{"playerId":260162.0,"info":{"position":"M","positionInfo":"Centre Central Midfielder","loan":false},"nationalTeam":{"isoCode":"GB-ENG","country":"England","demonym":"English"},"currentTeam":{"name":"Manchester City","club":{"name":"Manchester City","abbr":"MCI","id":11.0},"teamType":"FIRST","shortName":"Man City","id":11.0},"birth":{"date":{"millis":9.59472E11,"label":"28 May 2000"},"country":{"isoCode":"GB-ENG","country":"England","demonym":"English"},"place":"Stockport"},"age":"25 years 51 days","name":{"display":"Phil Foden","first":"Phil","last":"Foden"},"id":14805.0},"rank":4.0,"name":"goals","value":19.0,"description":"Todo: goals","additionalInfo":{}},{"owner":{"playerId":362647.0,"info":{"position":"F","shirtNum":19.0,"positionInfo":"Striker","loan":false},"nationalTeam":{"isoCode":"GB-ENG","country":"England","demonym":"English"},"birth":{"date":{"millis":8.741952E11,"label":"14 September 1997"},"country":{"isoCode":"GB-ENG","country":"England","demonym":"English"},"place":"Reading"},"age":"27 years 307 days","name":{"display":"Dominic Solanke","first":"Dominic","middle":"Ayodele","last":"Solanke"},"id":10443.0},"rank":4.0,"name":"goals","value":19.0,"description":"Todo: goals","additionalInfo":{}},{"owner":{"playerId":226363.0,"info":{"position":"F","shirtNum":11.0,"positionInfo":"Left/Centre/Right Second Striker","loan":false},"nationalTeam":{"isoCode":"GB-ENG","country":"England","demonym":"English"},"currentTeam":{"name":"Aston Villa","club":{"name":"Aston Villa","abbr":"AVL","id":2.0},"teamType":"FIRST","shortName":"Aston Villa","id":2.0},"birth":{"date":{"millis":8.202816E11,"label":"30 December 1995"},"country":{"isoCode":"GB-ENG","country":"England","demonym":"English"},"place":"Torquay"},"age":"29 years 200 days","name":{"display":"Ollie Watkins","first":"Ollie","last":"Watkins"},"id":8658.0},"rank":4.0,"name":"goals","value":19.0,"description":"Todo: goals","additionalInfo":{}},{"owner":{"playerId":47184.0,"info":{"position":"F","shirtNum":11.0,"positionInfo":"Left/Centre/Right Winger","loan":false},"nationalTeam":{"isoCode":"EG","country":"Egypt","demonym":"Egyptian"},"currentTeam":{"name":"Liverpool","club":{"name":"Liverpool","abbr":"LIV","id":10.0},"teamType":"FIRST","shortName":"Liverpool","id":10.0},"birth":{"date":{"millis":7.085664E11,"label":"15 June 1992"},"country":{"isoCode":"EG","country":"Egypt","demonym":"Egyptian"},"place":"Nagrig"},"age":"33 years 33 days","name":{"display":"Mohamed Salah","first":"Mohamed","last":"Salah Hamed Mahrous Ghaly"},"id":5178.0},"rank":7.0,"name":"goals","value":18.0,"description":"Todo: goals","additionalInfo":{}},{"owner":{"playerId":20239.0,"info":{"position":"F","shirtNum":7.0,"positionInfo":"Left/Centre/Right Winger","loan":false},"nationalTeam":{"isoCode":"KR","country":"South Korea","demonym":"Korean"},"currentTeam":{"name":"Tottenham Hotspur","club":{"name":"Tottenham Hotspur","abbr":"TOT","id":21.0},"teamType":"FIRST","shortName":"Spurs","id":21.0},"birth":{"date":{"millis":7.105536E11,"label":"8 July 1992"},"country":{"isoCode":"KR","country":"South Korea","demonym":"Korean"},"place":"Chuncheon"},"age":"33 years 10 days","name":{"display":"Son Heung-Min","first":"Heung-Min","last":"Son"},"id":4999.0},"rank":8.0,"name":"goals","value":17.0,"description":"Todo: goals","additionalInfo":{}},{"owner":{"playerId":180212.0,"info":{"position":"F","shirtNum":20.0,"positionInfo":"Centre Striker","loan":false},"nationalTeam":{"isoCode":"GB-ENG","country":"England","demonym":"English"},"currentTeam":{"name":"West Ham United","club":{"name":"West Ham United","abbr":"WHU","id":25.0},"teamType":"FIRST","shortName":"West Ham","id":25.0},"birth":{"date":{"millis":8.5104E11,"label":"20 December 1996"},"country":{"isoCode":"GB-ENG","country":"England","demonym":"English"},"place":"Leominster"},"age":"28 years 210 days","name":{"display":"Jarrod Bowen","first":"Jarrod","last":"Bowen"},"id":8868.0},"rank":9.0,"name":"goals","value":16.0,"description":"Todo: goals","additionalInfo":{}},{"owner":{"playerId":302911.0,"info":{"position":"F","shirtNum":14.0,"positionInfo":"Centre Striker","loan":false},"nationalTeam":{"isoCode":"FR","country":"France","demonym":"French"},"currentTeam":{"name":"Crystal Palace","club":{"name":"Crystal Palace","abbr":"CRY","id":6.0},"teamType":"FIRST","shortName":"Crystal Palace","id":6.0},"birth":{"date":{"millis":8.67456E11,"label":"28 June 1997"},"country":{"isoCode":"FR","country":"France","demonym":"French"},"place":"Sevran"},"age":"28 years 20 days","name":{"display":"Jean-Philippe Mateta","first":"Jean-Philippe","last":"Mateta"},"id":20874.0},"rank":9.0,"name":"goals","value":16.0,"description":"Todo: goals","additionalInfo":{}},{"owner":{"playerId":135654.0,"info":{"position":"F","shirtNum":77.0,"positionInfo":"Left Winger","loan":false},"nationalTeam":{"isoCode":"GB-ENG","country":"England","demonym":"English"},"currentTeam":{"name":"Arsenal","club":{"name":"Arsenal","abbr":"ARS","id":1.0},"teamType":"FIRST","shortName":"Arsenal","id":1.0},"birth":{"date":{"millis":9.99648E11,"label":"5 September 2001"},"country":{"isoCode":"GB-ENG","country":"England","demonym":"English"},"place":"London"},"age":"23 years 316 days","name":{"display":"Bukayo Saka","first":"Bukayo","last":"Saka"},"id":49481.0},"rank":9.0,"name":"goals","value":16.0,"description":"Todo: goals","additionalInfo":{}},{"owner":{"playerId":340743.0,"info":{"position":"F","shirtNum":15.0,"positionInfo":"Centre Second Striker","loan":false},"nationalTeam":{"isoCode":"SN","country":"Senegal","demonym":"Senegalese"},"currentTeam":{"name":"Chelsea","club":{"name":"Chelsea","abbr":"CHE","id":4.0},"teamType":"FIRST","shortName":"Chelsea","id":4.0},"birth":{"date":{"millis":9.929952E11,"label":"20 June 2001"},"country":{"isoCode":"GM","country":"Gambia","demonym":"Gambian"},"place":"Banjul"},"age":"24 years 28 days","name":{"display":"Nicolas Jackson","first":"Nicolas","last":"Jackson"},"id":110526.0},"rank":12.0,"name":"goals","value":14.0,"description":"Todo: goals","additionalInfo":{}},{"owner":{"playerId":340567.0,"info":{"position":"F","shirtNum":11.0,"positionInfo":"Centre Striker","loan":false},"nationalTeam":{"isoCode":"NZ","country":"New Zealand","demonym":"New Zealander"},"currentTeam":{"name":"Nottingham Forest","club":{"name":"Nottingham Forest","abbr":"NFO","id":15.0},"teamType":"FIRST","shortName":"Nott\u0027m Forest","id":15.0},"birth":{"date":{"millis":6.92064E11,"label":"7 December 1991"},"country":{"isoCode":"NZ","country":"New Zealand","demonym":"New Zealander"},"place":"Auckland"},"age":"33 years 223 days","name":{"display":"Chris Wood","first":"Chris","last":"Wood"},"id":3756.0},"rank":12.0,"name":"goals","value":14.0,"description":"Todo: goals","additionalInfo":{}},{"owner":{"playerId":340669.0,"info":{"position":"F","shirtNum":29.0,"positionInfo":"Left/Centre/Right Second Striker","loan":false},"nationalTeam":{"isoCode":"DE","country":"Germany","demonym":"German"},"currentTeam":{"name":"Arsenal","club":{"name":"Arsenal","abbr":"ARS","id":1.0},"teamType":"FIRST","shortName":"Arsenal","id":1.0},"birth":{"date":{"millis":9.290592E11,"label":"11 June 1999"},"country":{"isoCode":"DE","country":"Germany","demonym":"German"},"place":"Aachen"},"age":"26 years 37 days","name":{"display":"Kai Havertz","first":"Kai","last":"Havertz"},"id":20810.0},"rank":14.0,"name":"goals","value":13.0,"description":"Todo: goals","additionalInfo":{}},{"owner":{"playerId":312590.0,"info":{"position":"F","shirtNum":11.0,"positionInfo":"Centre Striker","loan":false},"nationalTeam":{"isoCode":"KR","country":"South Korea","demonym":"Korean"},"currentTeam":{"name":"Wolverhampton Wanderers","club":{"name":"Wolverhampton Wanderers","abbr":"WOL","id":38.0},"teamType":"FIRST","shortName":"Wolves","id":38.0},"birth":{"date":{"millis":8.226144E11,"label":"26 January 1996"},"country":{"isoCode":"KR","country":"South Korea","demonym":"Korean"},"place":"Chuncheon"},"age":"29 years 173 days","name":{"display":"Hwang Hee-Chan","first":"Hee-Chan","last":"Hwang"},"id":20337.0},"rank":15.0,"name":"goals","value":12.0,"description":"Todo: goals","additionalInfo":{}},{"owner":{"playerId":736964.0,"info":{"position":"F","shirtNum":10.0,"positionInfo":"Left/Centre Second Striker","loan":false},"nationalTeam":{"isoCode":"BR","country":"Brazil","demonym":"Brazilian"},"birth":{"date":{"millis":9.277632E11,"label":"27 May 1999"},"country":{"isoCode":"BR","country":"Brazil","demonym":"Brazilian"},"place":"João Pessoa"},"age":"26 years 52 days","name":{"display":"Matheus Cunha","first":"Matheus","last":"Santos Carneiro da Cunha"},"id":51202.0},"rank":15.0,"name":"goals","value":12.0,"description":"Todo: goals","additionalInfo":{}},{"owner":{"playerId":336745.0,"info":{"position":"F","shirtNum":19.0,"positionInfo":"Forward","loan":false},"nationalTeam":{"isoCode":"BE","country":"Belgium","demonym":"Belgian"},"currentTeam":{"name":"Arsenal","club":{"name":"Arsenal","abbr":"ARS","id":1.0},"teamType":"FIRST","shortName":"Arsenal","id":1.0},"birth":{"date":{"millis":7.864992E11,"label":"4 December 1994"},"country":{"isoCode":"BE","country":"Belgium","demonym":"Belgian"},"place":"Maasmechelen"},"age":"30 years 226 days","name":{"display":"Leandro Trossard","first":"Leandro","last":"Trossard"},"id":20486.0},"rank":15.0,"name":"goals","value":12.0,"description":"Todo: goals","additionalInfo":{}},{"owner":{"playerId":286396.0,"info":{"position":"M","shirtNum":11.0,"positionInfo":"Left Winger","loan":false},"nationalTeam":{"isoCode":"CD","country":"DR Congo","demonym":"Congolese"},"currentTeam":{"name":"Brentford","club":{"name":"Brentford","abbr":"BRE","id":130.0},"teamType":"FIRST","shortName":"Brentford","id":130.0},"birth":{"date":{"millis":8.417088E11,"label":"3 September 1996"},"country":{"isoCode":"FR","country":"France","demonym":"French"},"place":"Épinay-sous-Sénart"},"age":"28 years 318 days","name":{"display":"Yoane Wissa","first":"Yoane","last":"Wissa"},"id":117497.0},"rank":15.0,"name":"goals","value":12.0,"description":"Todo: goals","additionalInfo":{}},{"owner":{"playerId":362733.0,"info":{"position":"F","shirtNum":19.0,"positionInfo":"Centre Striker","loan":false},"nationalTeam":{"isoCode":"AR","country":"Argentina"},"birth":{"date":{"millis":9.492768E11,"label":"31 January 2000"},"country":{"isoCode":"AR","country":"Argentina"},"place":"Calchín"},"age":"25 years 168 days","name":{"display":"Julián Alvarez","first":"Julián","last":"Alvarez"},"id":52723.0},"rank":19.0,"name":"goals","value":11.0,"description":"Todo: goals","additionalInfo":{}},{"owner":{"playerId":314636.0,"info":{"position":"F","shirtNum":9.0,"positionInfo":"Left/Centre/Right Second Striker","loan":false},"nationalTeam":{"isoCode":"BR","country":"Brazil","demonym":"Brazilian"},"currentTeam":{"name":"Tottenham Hotspur","club":{"name":"Tottenham Hotspur","abbr":"TOT","id":21.0},"teamType":"FIRST","shortName":"Spurs","id":21.0},"birth":{"date":{"millis":8.632224E11,"label":"10 May 1997"},"country":{"isoCode":"BR","country":"Brazil","demonym":"Brazilian"},"place":"Nova Venécia"},"age":"28 years 69 days","name":{"display":"Richarlison","first":"Richarlison","last":"de Andrade"},"id":24630.0},"rank":19.0,"name":"goals","value":11.0,"description":"Todo: goals","additionalInfo":{}},{"owner":{"playerId":320724.0,"info":{"position":"M","shirtNum":10.0,"positionInfo":"Centre Attacking Midfielder","loan":false},"nationalTeam":{"isoCode":"GB-ENG","country":"England","demonym":"English"},"currentTeam":{"name":"Crystal Palace","club":{"name":"Crystal Palace","abbr":"CRY","id":6.0},"teamType":"FIRST","shortName":"Crystal Palace","id":6.0},"birth":{"date":{"millis":8.990784E11,"label":"29 June 1998"},"country":{"isoCode":"GB-ENG","country":"England","demonym":"English"},"place":"London"},"age":"27 years 19 days","name":{"display":"Eberechi Eze","first":"Eberechi","last":"Eze"},"id":21584.0},"rank":19.0,"name":"goals","value":11.0,"description":"Todo: goals","additionalInfo":{}},{"owner":{"playerId":337516.0,"info":{"position":"F","shirtNum":10.0,"positionInfo":"Winger","loan":false},"nationalTeam":{"isoCode":"GB-ENG","country":"England","demonym":"English"},"currentTeam":{"name":"Newcastle United","club":{"name":"Newcastle United","abbr":"NEW","id":23.0},"teamType":"FIRST","shortName":"Newcastle","id":23.0},"birth":{"date":{"millis":9.829728E11,"label":"24 February 2001"},"country":{"isoCode":"GB-ENG","country":"England","demonym":"English"},"place":"Liverpool"},"age":"24 years 144 days","name":{"display":"Anthony Gordon","first":"Anthony","last":"Gordon"},"id":23747.0},"rank":19.0,"name":"goals","value":11.0,"description":"Todo: goals","additionalInfo":{}},{"owner":{"playerId":737241.0,"info":{"position":"F","positionInfo":"Forward","loan":false},"nationalTeam":{"isoCode":"GB-ENG","country":"England","demonym":"English"},"currentTeam":{"name":"Luton Town","club":{"name":"Luton Town","abbr":"LUT","id":163.0},"teamType":"FIRST","shortName":"Luton","id":163.0},"birth":{"date":{"millis":8.19072E11,"label":"16 December 1995"},"country":{"isoCode":"GB-ENG","country":"England","demonym":"English"},"place":"Cambridge"},"age":"29 years 214 days","name":{"display":"Carlton Morris","first":"Carlton","last":"Morris"},"id":11008.0},"rank":19.0,"name":"goals","value":11.0,"description":"Todo: goals","additionalInfo":{}},{"owner":{"playerId":312801.0,"info":{"position":"F","shirtNum":9.0,"positionInfo":"Centre Striker","loan":false},"nationalTeam":{"isoCode":"UY","country":"Uruguay","demonym":"Uruguayan"},"currentTeam":{"name":"Liverpool","club":{"name":"Liverpool","abbr":"LIV","id":10.0},"teamType":"FIRST","shortName":"Liverpool","id":10.0},"birth":{"date":{"millis":9.301824E11,"label":"24 June 1999"},"country":{"isoCode":"UY","country":"Uruguay","demonym":"Uruguayan"},"place":"Artigas"},"age":"26 years 24 days","name":{"display":"Darwin Núñez","first":"Darwin","middle":"Gabriel","last":"Núñez"},"id":70287.0},"rank":19.0,"name":"goals","value":11.0,"description":"Todo: goals","additionalInfo":{}},{"owner":{"playerId":268672.0,"info":{"position":"F","shirtNum":11.0,"positionInfo":"Centre Striker","loan":false},"nationalTeam":{"isoCode":"GB-ENG","country":"England","demonym":"English"},"currentTeam":{"name":"Luton Town","club":{"name":"Luton Town","abbr":"LUT","id":163.0},"teamType":"FIRST","shortName":"Luton","id":163.0},"birth":{"date":{"millis":8.841312E11,"label":"7 January 1998"},"country":{"isoCode":"GB-ENG","country":"England","demonym":"English"},"place":"London"},"age":"27 years 192 days","name":{"display":"Elijah Adebayo","first":"Elijah","last":"Adebayo"},"id":14685.0},"rank":25.0,"name":"goals","value":10.0,"description":"Todo: goals","additionalInfo":{}}]}}